misc.py
mydatasets.py
aspectnlp/__init__.py
aspectnlp/aspect_detector.py
aspectnlp/aspect_sentiment.py
aspectnlp/models.py
aspectnlp/utils.py
aspectnlp/vae_topic_model.py
aspectnlp/w2v.py
aspectnlp/absa_embedding/__init__.py
aspectnlp/absa_model/__init__.py
aspectnlp/absa_model/custom
aspectnlp/absa_model/custom_info.pkl
aspectnlp/absa_prep/__init__.py
aspectnlp/absa_prep/custom_emb.vec.npy
aspectnlp/absa_prep/gen.vec.npy
aspectnlp/absa_prep/word_idx.json
aspectnlp/config/__init__.py
aspectnlp/config/config_custom.py
aspectnlp/config/config_customAS.py
aspectnlp/config/config_snapshot.py
aspectnlp/embeddings/glove_words_compressed.npy
aspectnlp/models/customAS_as.pt
aspectnlp/models/customAS_final.pt
aspectnlp/models/customAS_sm.pt
aspectnlp/models/customAS_text.pt
aspectnlp-0.0.4.dist-info/LICENSE
aspectnlp-0.0.4.dist-info/METADATA
aspectnlp-0.0.4.dist-info/WHEEL
aspectnlp-0.0.4.dist-info/top_level.txt
aspectnlp-0.0.4.dist-info/RECORD
