Metadata-Version: 2.1
Name: aspectnlp
Version: 0.0.4
Summary: Aspect detection NLP toolkit is a Python package that perform NLP tasks based on aspect detection.
Home-page: UNKNOWN
Author: Shuanglu Dai
Author-email: shuanglu.dai@gmail.com
License: UNKNOWN
Keywords: aspectnlp
Platform: UNKNOWN
Classifier: Development Status :: 2 - Pre-Alpha
Classifier: Intended Audience :: Developers
Classifier: Natural Language :: English
Classifier: Programming Language :: Python :: 3.7
Classifier: Programming Language :: Python :: 3.8
Classifier: License :: OSI Approved :: MIT License
Requires-Dist: nltk (==3.2.5)
Requires-Dist: wheel (==0.36.2)
Requires-Dist: gensim (==3.8.3)
Requires-Dist: textblob (==0.15.3)
Requires-Dist: torch (==1.7.0+cpu)
Requires-Dist: fasttext (==0.9.2)
Requires-Dist: keras (==2.3.1)
Requires-Dist: torchtext (==0.2.3)
Requires-Dist: dill (==0.3.3)
Requires-Dist: tensorflow (==2.3.1)
